{
    "Name":  "AMSMediaAccountHealth",
    "Properties":  [
                       {
                           "Name":  "TimeGenerated",
                           "Type":  "DateTime"
                       },
                       {
                           "Name":  "TenantId",
                           "Type":  "Guid"
                       },
                       {
                           "Name":  "OperationName",
                           "Type":  "String"
                       },
                       {
                           "Name":  "Level",
                           "Type":  "String"
                       },
                       {
                           "Name":  "Location",
                           "Type":  "String"
                       },
                       {
                           "Name":  "EventCode",
                           "Type":  "String"
                       },
                       {
                           "Name":  "EventMessage",
                           "Type":  "String"
                       },
                       {
                           "Name":  "SourceSystem",
                           "Type":  "String"
                       },
                       {
                           "Name":  "Type",
                           "Type":  "String"
                       },
                       {
                           "Name":  "_ResourceId",
                           "Type":  "String"
                       }
                   ]
}
